<?xml version = "1.0" encoding="Windows-1252" standalone="yes"?>
<VFPData>
	<diccionarioentidad>
		<entidad>ITEMVALORESNDCOMPRA</entidad>
		<atributo>Codigo</atributo>
		<tabla>ValNdComp</tabla>
		<campo>JJNUM</campo>
		<alta>false</alta>
		<tipodato>G</tipodato>
		<longitud>38</longitud>
		<decimales>0</decimales>
		<dominio>CODIGO</dominio>
		<claveprimaria>true</claveprimaria>
		<claveforanea/>
		<muestrarelacion>false</muestrarelacion>
		<valorsugerido/>
		<obligatorio>false</obligatorio>
		<atributoforaneo/>
	</diccionarioentidad>
	<diccionarioentidad>
		<entidad>ITEMVALORESNDCOMPRA</entidad>
		<atributo>Cotiza</atributo>
		<tabla>ValNdComp</tabla>
		<campo>JJCotiz</campo>
		<alta>false</alta>
		<tipodato>N</tipodato>
		<longitud>15</longitud>
		<decimales>5</decimales>
		<dominio>NUMERICO</dominio>
		<claveprimaria>false</claveprimaria>
		<claveforanea/>
		<muestrarelacion>false</muestrarelacion>
		<valorsugerido/>
		<obligatorio>false</obligatorio>
		<atributoforaneo/>
	</diccionarioentidad>
	<diccionarioentidad>
		<entidad>ITEMVALORESNDCOMPRA</entidad>
		<atributo>FechaComp</atributo>
		<tabla>ValNdComp</tabla>
		<campo>JJfecha</campo>
		<alta>false</alta>
		<tipodato>D</tipodato>
		<longitud>8</longitud>
		<decimales>0</decimales>
		<dominio>FECHA</dominio>
		<claveprimaria>false</claveprimaria>
		<claveforanea/>
		<muestrarelacion>false</muestrarelacion>
		<valorsugerido/>
		<obligatorio>false</obligatorio>
		<atributoforaneo/>
	</diccionarioentidad>
	<diccionarioentidad>
		<entidad>ITEMVALORESNDCOMPRA</entidad>
		<atributo>Letra</atributo>
		<tabla>ValNdComp</tabla>
		<campo>Letra</campo>
		<alta>false</alta>
		<tipodato>C</tipodato>
		<longitud>1</longitud>
		<decimales>0</decimales>
		<dominio>CARACTER</dominio>
		<claveprimaria>false</claveprimaria>
		<claveforanea/>
		<muestrarelacion>false</muestrarelacion>
		<valorsugerido/>
		<obligatorio>false</obligatorio>
		<atributoforaneo/>
	</diccionarioentidad>
	<diccionarioentidad>
		<entidad>ITEMVALORESNDCOMPRA</entidad>
		<atributo>NroDocumento</atributo>
		<tabla>ValNdComp</tabla>
		<campo>NroDoc</campo>
		<alta>false</alta>
		<tipodato>C</tipodato>
		<longitud>10</longitud>
		<decimales>0</decimales>
		<dominio>CARACTER</dominio>
		<claveprimaria>false</claveprimaria>
		<claveforanea/>
		<muestrarelacion>false</muestrarelacion>
		<valorsugerido/>
		<obligatorio>false</obligatorio>
		<atributoforaneo/>
	</diccionarioentidad>
	<diccionarioentidad>
		<entidad>ITEMVALORESNDCOMPRA</entidad>
		<atributo>NroItem</atributo>
		<tabla>ValNdComp</tabla>
		<campo>NroItem</campo>
		<alta>false</alta>
		<tipodato>N</tipodato>
		<longitud>5</longitud>
		<decimales>0</decimales>
		<dominio>NUMERICO</dominio>
		<claveprimaria>false</claveprimaria>
		<claveforanea/>
		<muestrarelacion>false</muestrarelacion>
		<valorsugerido/>
		<obligatorio>false</obligatorio>
		<atributoforaneo/>
	</diccionarioentidad>
	<diccionarioentidad>
		<entidad>ITEMVALORESNDCOMPRA</entidad>
		<atributo>NumeroCheque</atributo>
		<tabla>ValNdComp</tabla>
		<campo>NroCheque</campo>
		<alta>false</alta>
		<tipodato>G</tipodato>
		<longitud>38</longitud>
		<decimales>0</decimales>
		<dominio>CODIGO</dominio>
		<claveprimaria>false</claveprimaria>
		<claveforanea>CHEQUE</claveforanea>
		<muestrarelacion>false</muestrarelacion>
		<valorsugerido/>
		<obligatorio>false</obligatorio>
		<atributoforaneo/>
	</diccionarioentidad>
	<diccionarioentidad>
		<entidad>ITEMVALORESNDCOMPRA</entidad>
		<atributo>NumeroCupon</atributo>
		<tabla>ValNdComp</tabla>
		<campo>NroCupon</campo>
		<alta>false</alta>
		<tipodato>N</tipodato>
		<longitud>5</longitud>
		<decimales>0</decimales>
		<dominio>NUMERICO</dominio>
		<claveprimaria>false</claveprimaria>
		<claveforanea/>
		<muestrarelacion>false</muestrarelacion>
		<valorsugerido/>
		<obligatorio>false</obligatorio>
		<atributoforaneo/>
	</diccionarioentidad>
	<diccionarioentidad>
		<entidad>ITEMVALORESNDCOMPRA</entidad>
		<atributo>NumeroTarjeta</atributo>
		<tabla>ValNdComp</tabla>
		<campo>NroTarjeta</campo>
		<alta>false</alta>
		<tipodato>C</tipodato>
		<longitud>25</longitud>
		<decimales>0</decimales>
		<dominio>CARACTER</dominio>
		<claveprimaria>false</claveprimaria>
		<claveforanea/>
		<muestrarelacion>false</muestrarelacion>
		<valorsugerido/>
		<obligatorio>false</obligatorio>
		<atributoforaneo/>
	</diccionarioentidad>
	<diccionarioentidad>
		<entidad>ITEMVALORESNDCOMPRA</entidad>
		<atributo>NumerodeComprobante</atributo>
		<tabla>ValNdComp</tabla>
		<campo>NumCompr</campo>
		<alta>false</alta>
		<tipodato>N</tipodato>
		<longitud>8</longitud>
		<decimales>0</decimales>
		<dominio>NUMERICO</dominio>
		<claveprimaria>false</claveprimaria>
		<claveforanea/>
		<muestrarelacion>false</muestrarelacion>
		<valorsugerido/>
		<obligatorio>false</obligatorio>
		<atributoforaneo/>
	</diccionarioentidad>
	<diccionarioentidad>
		<entidad>ITEMVALORESNDCOMPRA</entidad>
		<atributo>PesosAlCambio</atributo>
		<tabla>ValNdComp</tabla>
		<campo>Pesos</campo>
		<alta>false</alta>
		<tipodato>N</tipodato>
		<longitud>15</longitud>
		<decimales>2</decimales>
		<dominio>NUMERICO</dominio>
		<claveprimaria>false</claveprimaria>
		<claveforanea/>
		<muestrarelacion>false</muestrarelacion>
		<valorsugerido/>
		<obligatorio>false</obligatorio>
		<atributoforaneo/>
	</diccionarioentidad>
	<diccionarioentidad>
		<entidad>ITEMVALORESNDCOMPRA</entidad>
		<atributo>PuntoDeVenta</atributo>
		<tabla>ValNdComp</tabla>
		<campo>PtoVenta</campo>
		<alta>false</alta>
		<tipodato>N</tipodato>
		<longitud>4</longitud>
		<decimales>0</decimales>
		<dominio>NUMERICO</dominio>
		<claveprimaria>false</claveprimaria>
		<claveforanea/>
		<muestrarelacion>false</muestrarelacion>
		<valorsugerido/>
		<obligatorio>false</obligatorio>
		<atributoforaneo/>
	</diccionarioentidad>
	<diccionarioentidad>
		<entidad>ITEMVALORESNDCOMPRA</entidad>
		<atributo>Signo</atributo>
		<tabla>ValNdComp</tabla>
		<campo>Signo</campo>
		<alta>false</alta>
		<tipodato>N</tipodato>
		<longitud>2</longitud>
		<decimales>0</decimales>
		<dominio>NUMERICO</dominio>
		<claveprimaria>false</claveprimaria>
		<claveforanea/>
		<muestrarelacion>false</muestrarelacion>
		<valorsugerido/>
		<obligatorio>false</obligatorio>
		<atributoforaneo/>
	</diccionarioentidad>
	<diccionarioentidad>
		<entidad>ITEMVALORESNDCOMPRA</entidad>
		<atributo>Tipo</atributo>
		<tabla>ValNdComp</tabla>
		<campo>JJT</campo>
		<alta>false</alta>
		<tipodato>N</tipodato>
		<longitud>2</longitud>
		<decimales>0</decimales>
		<dominio>NUMERICO</dominio>
		<claveprimaria>false</claveprimaria>
		<claveforanea/>
		<muestrarelacion>false</muestrarelacion>
		<valorsugerido/>
		<obligatorio>false</obligatorio>
		<atributoforaneo>Valor.Tipo</atributoforaneo>
	</diccionarioentidad>
	<diccionarioentidad>
		<entidad>ITEMVALORESNDCOMPRA</entidad>
		<atributo>TipoDocumento</atributo>
		<tabla>ValNdComp</tabla>
		<campo>TipoDoc</campo>
		<alta>false</alta>
		<tipodato>C</tipodato>
		<longitud>2</longitud>
		<decimales>0</decimales>
		<dominio>CARACTER</dominio>
		<claveprimaria>false</claveprimaria>
		<claveforanea/>
		<muestrarelacion>false</muestrarelacion>
		<valorsugerido/>
		<obligatorio>false</obligatorio>
		<atributoforaneo/>
	</diccionarioentidad>
	<diccionarioentidad>
		<entidad>ITEMVALORESNDCOMPRA</entidad>
		<atributo>TipodeComprobante</atributo>
		<tabla>ValNdComp</tabla>
		<campo>TIPCOMP</campo>
		<alta>false</alta>
		<tipodato>C</tipodato>
		<longitud>3</longitud>
		<decimales>0</decimales>
		<dominio>CARACTER</dominio>
		<claveprimaria>false</claveprimaria>
		<claveforanea/>
		<muestrarelacion>false</muestrarelacion>
		<valorsugerido/>
		<obligatorio>false</obligatorio>
		<atributoforaneo/>
	</diccionarioentidad>
	<diccionarioentidad>
		<entidad>ITEMVALORESNDCOMPRA</entidad>
		<atributo>Turno</atributo>
		<tabla>ValNdComp</tabla>
		<campo>JJTurno</campo>
		<alta>false</alta>
		<tipodato>N</tipodato>
		<longitud>1</longitud>
		<decimales>0</decimales>
		<dominio>NUMERICO</dominio>
		<claveprimaria>false</claveprimaria>
		<claveforanea/>
		<muestrarelacion>false</muestrarelacion>
		<valorsugerido/>
		<obligatorio>false</obligatorio>
		<atributoforaneo/>
	</diccionarioentidad>
	<diccionarioentidad>
		<entidad>ITEMVALORESNDCOMPRA</entidad>
		<atributo>Valor</atributo>
		<tabla>ValNdComp</tabla>
		<campo>JJCO</campo>
		<alta>true</alta>
		<tipodato>C</tipodato>
		<longitud>5</longitud>
		<decimales>0</decimales>
		<dominio>CODIGOVALOR</dominio>
		<claveprimaria>false</claveprimaria>
		<claveforanea>VALOR</claveforanea>
		<muestrarelacion>false</muestrarelacion>
		<valorsugerido/>
		<obligatorio>true</obligatorio>
		<atributoforaneo/>
	</diccionarioentidad>
	<diccionarioentidad>
		<entidad>ITEMVALORESNDCOMPRA</entidad>
		<atributo>Vendedor</atributo>
		<tabla>ValNdComp</tabla>
		<campo>JJVen</campo>
		<alta>false</alta>
		<tipodato>C</tipodato>
		<longitud>5</longitud>
		<decimales>0</decimales>
		<dominio>CARACTER</dominio>
		<claveprimaria>false</claveprimaria>
		<claveforanea/>
		<muestrarelacion>false</muestrarelacion>
		<valorsugerido/>
		<obligatorio>false</obligatorio>
		<atributoforaneo/>
	</diccionarioentidad>
	<diccionarioentidad>
		<entidad>ITEMVALORESNDCOMPRA</entidad>
		<atributo>FechaUltCotizacion</atributo>
		<tabla>ValNdComp</tabla>
		<campo>FechCoti</campo>
		<alta>false</alta>
		<tipodato>D</tipodato>
		<longitud>8</longitud>
		<decimales>0</decimales>
		<dominio>FECHA</dominio>
		<claveprimaria>false</claveprimaria>
		<claveforanea/>
		<muestrarelacion>false</muestrarelacion>
		<valorsugerido/>
		<obligatorio>false</obligatorio>
		<atributoforaneo/>
	</diccionarioentidad>
	<diccionarioentidad>
		<entidad>ITEMVALORESNDCOMPRA</entidad>
		<atributo>UltimaCotizacion</atributo>
		<tabla>ValNdComp</tabla>
		<campo>Cotiza</campo>
		<alta>false</alta>
		<tipodato>N</tipodato>
		<longitud>15</longitud>
		<decimales>5</decimales>
		<dominio>NUMERICO</dominio>
		<claveprimaria>false</claveprimaria>
		<claveforanea/>
		<muestrarelacion>false</muestrarelacion>
		<valorsugerido/>
		<obligatorio>false</obligatorio>
		<atributoforaneo/>
	</diccionarioentidad>
	<diccionarioentidad>
		<entidad>ITEMVALORESNDCOMPRA</entidad>
		<atributo>Caja</atributo>
		<tabla>ValNdComp</tabla>
		<campo>IdCaja</campo>
		<alta>false</alta>
		<tipodato>N</tipodato>
		<longitud>2</longitud>
		<decimales>0</decimales>
		<dominio>CODIGONUMERICO</dominio>
		<claveprimaria>false</claveprimaria>
		<claveforanea>CAJAESTADO</claveforanea>
		<muestrarelacion>false</muestrarelacion>
		<valorsugerido/>
		<obligatorio>false</obligatorio>
		<atributoforaneo/>
	</diccionarioentidad>
	<diccionarioentidad>
		<entidad>ITEMVALORESNDCOMPRA</entidad>
		<atributo>PersonalizarComprobante</atributo>
		<tabla>ValNdComp</tabla>
		<campo>PersComp</campo>
		<alta>false</alta>
		<tipodato>L</tipodato>
		<longitud>1</longitud>
		<decimales>0</decimales>
		<dominio>SINOBOOL</dominio>
		<claveprimaria>false</claveprimaria>
		<claveforanea/>
		<muestrarelacion>false</muestrarelacion>
		<valorsugerido/>
		<obligatorio>false</obligatorio>
		<atributoforaneo>Valor.PersonalizarComprobante</atributoforaneo>
	</diccionarioentidad>
	<diccionarioentidad>
		<entidad>ITEMVALORESNDCOMPRA</entidad>
		<atributo>CondicionRecargo</atributo>
		<tabla/>
		<campo/>
		<alta>false</alta>
		<tipodato>N</tipodato>
		<longitud>1</longitud>
		<decimales>0</decimales>
		<dominio>NUMERICO</dominio>
		<claveprimaria>false</claveprimaria>
		<claveforanea/>
		<muestrarelacion>false</muestrarelacion>
		<valorsugerido>=2</valorsugerido>
		<obligatorio>false</obligatorio>
		<atributoforaneo/>
	</diccionarioentidad>
	<diccionarioentidad>
		<entidad>ITEMVALORESNDCOMPRA</entidad>
		<atributo>NumeroChequePropio</atributo>
		<tabla>ValNdComp</tabla>
		<campo>NroChProp</campo>
		<alta>false</alta>
		<tipodato>G</tipodato>
		<longitud>38</longitud>
		<decimales>0</decimales>
		<dominio>CODIGO</dominio>
		<claveprimaria>false</claveprimaria>
		<claveforanea>CHEQUEPROPIO</claveforanea>
		<muestrarelacion>false</muestrarelacion>
		<valorsugerido/>
		<obligatorio>false</obligatorio>
		<atributoforaneo/>
	</diccionarioentidad>
	<diccionarioentidad>
		<entidad>ITEMVALORESNDCOMPRA</entidad>
		<atributo>CondicionDePago</atributo>
		<tabla>ValNdComp</tabla>
		<campo>CondPago</campo>
		<alta>false</alta>
		<tipodato>C</tipodato>
		<longitud>5</longitud>
		<decimales>0</decimales>
		<dominio>CODIGO</dominio>
		<claveprimaria>false</claveprimaria>
		<claveforanea>CONDICIONDEPAGO</claveforanea>
		<muestrarelacion>false</muestrarelacion>
		<valorsugerido/>
		<obligatorio>false</obligatorio>
		<atributoforaneo/>
	</diccionarioentidad>
	<diccionarioentidad>
		<entidad>ITEMVALORESNDCOMPRA</entidad>
		<atributo>VisualizarEnEstadoDeCaja</atributo>
		<tabla>ValNdComp</tabla>
		<campo>VisualCaja</campo>
		<alta>false</alta>
		<tipodato>L</tipodato>
		<longitud>1</longitud>
		<decimales>0</decimales>
		<dominio>SINOBOOL</dominio>
		<claveprimaria>false</claveprimaria>
		<claveforanea/>
		<muestrarelacion>false</muestrarelacion>
		<valorsugerido/>
		<obligatorio>false</obligatorio>
		<atributoforaneo>Valor.VisualizarEnCaja</atributoforaneo>
	</diccionarioentidad>
	<diccionarioentidad>
		<entidad>ITEMVALORESNDCOMPRA</entidad>
		<atributo>ChequeElectronico</atributo>
		<tabla>ValNdComp</tabla>
		<campo>CElectro</campo>
		<alta>false</alta>
		<tipodato>L</tipodato>
		<longitud>1</longitud>
		<decimales>0</decimales>
		<dominio>SINOBOOL</dominio>
		<claveprimaria>false</claveprimaria>
		<claveforanea/>
		<muestrarelacion>false</muestrarelacion>
		<valorsugerido/>
		<obligatorio>false</obligatorio>
		<atributoforaneo/>
	</diccionarioentidad>
	<diccionarioentidad>
		<entidad>ITEMVALORESNDCOMPRA</entidad>
		<atributo>ValorDetalle</atributo>
		<tabla>ValNdComp</tabla>
		<campo>JJDE</campo>
		<alta>true</alta>
		<tipodato>C</tipodato>
		<longitud>40</longitud>
		<decimales>0</decimales>
		<dominio>CARACTER</dominio>
		<claveprimaria>false</claveprimaria>
		<claveforanea/>
		<muestrarelacion>true</muestrarelacion>
		<valorsugerido/>
		<obligatorio>false</obligatorio>
		<atributoforaneo>Valor.Descripcion</atributoforaneo>
	</diccionarioentidad>
	<diccionarioentidad>
		<entidad>ITEMVALORESNDCOMPRA</entidad>
		<atributo>Fecha</atributo>
		<tabla>ValNdComp</tabla>
		<campo>JJFE</campo>
		<alta>true</alta>
		<tipodato>D</tipodato>
		<longitud>8</longitud>
		<decimales>0</decimales>
		<dominio>FECHA</dominio>
		<claveprimaria>false</claveprimaria>
		<claveforanea/>
		<muestrarelacion>false</muestrarelacion>
		<valorsugerido/>
		<obligatorio>false</obligatorio>
		<atributoforaneo/>
	</diccionarioentidad>
	<diccionarioentidad>
		<entidad>ITEMVALORESNDCOMPRA</entidad>
		<atributo>NumeroInterno</atributo>
		<tabla>ValNdComp</tabla>
		<campo>NroInterno</campo>
		<alta>true</alta>
		<tipodato>C</tipodato>
		<longitud>15</longitud>
		<decimales>0</decimales>
		<dominio>CARACTER</dominio>
		<claveprimaria>false</claveprimaria>
		<claveforanea/>
		<muestrarelacion>false</muestrarelacion>
		<valorsugerido/>
		<obligatorio>false</obligatorio>
		<atributoforaneo/>
	</diccionarioentidad>
	<diccionarioentidad>
		<entidad>ITEMVALORESNDCOMPRA</entidad>
		<atributo>Monto</atributo>
		<tabla>ValNdComp</tabla>
		<campo>JJM</campo>
		<alta>true</alta>
		<tipodato>N</tipodato>
		<longitud>15</longitud>
		<decimales>2</decimales>
		<dominio>NUMERICO</dominio>
		<claveprimaria>false</claveprimaria>
		<claveforanea/>
		<muestrarelacion>false</muestrarelacion>
		<valorsugerido/>
		<obligatorio>false</obligatorio>
		<atributoforaneo/>
	</diccionarioentidad>
	<diccionarioentidad>
		<entidad>ITEMVALORESNDCOMPRA</entidad>
		<atributo>MontoOri</atributo>
		<tabla/>
		<campo/>
		<alta>false</alta>
		<tipodato>N</tipodato>
		<longitud>15</longitud>
		<decimales>2</decimales>
		<dominio>NUMERICO</dominio>
		<claveprimaria>false</claveprimaria>
		<claveforanea/>
		<muestrarelacion>false</muestrarelacion>
		<valorsugerido/>
		<obligatorio>false</obligatorio>
		<atributoforaneo/>
	</diccionarioentidad>
	<diccionarioentidad>
		<entidad>ITEMVALORESNDCOMPRA</entidad>
		<atributo>RecargoPorcentaje</atributo>
		<tabla>ValNdComp</tabla>
		<campo>jrecporc</campo>
		<alta>true</alta>
		<tipodato>N</tipodato>
		<longitud>6</longitud>
		<decimales>2</decimales>
		<dominio>NUMERICO</dominio>
		<claveprimaria>false</claveprimaria>
		<claveforanea/>
		<muestrarelacion>false</muestrarelacion>
		<valorsugerido/>
		<obligatorio>false</obligatorio>
		<atributoforaneo/>
	</diccionarioentidad>
	<diccionarioentidad>
		<entidad>ITEMVALORESNDCOMPRA</entidad>
		<atributo>RecargoMonto</atributo>
		<tabla>ValNdComp</tabla>
		<campo>jrecmnt</campo>
		<alta>true</alta>
		<tipodato>N</tipodato>
		<longitud>8</longitud>
		<decimales>2</decimales>
		<dominio>NUMERICO</dominio>
		<claveprimaria>false</claveprimaria>
		<claveforanea/>
		<muestrarelacion>false</muestrarelacion>
		<valorsugerido/>
		<obligatorio>false</obligatorio>
		<atributoforaneo/>
	</diccionarioentidad>
	<diccionarioentidad>
		<entidad>ITEMVALORESNDCOMPRA</entidad>
		<atributo>Total</atributo>
		<tabla>ValNdComp</tabla>
		<campo>JJTotFac</campo>
		<alta>true</alta>
		<tipodato>N</tipodato>
		<longitud>15</longitud>
		<decimales>2</decimales>
		<dominio>NUMERICO</dominio>
		<claveprimaria>false</claveprimaria>
		<claveforanea/>
		<muestrarelacion>false</muestrarelacion>
		<valorsugerido/>
		<obligatorio>false</obligatorio>
		<atributoforaneo/>
	</diccionarioentidad>
	<diccionarioentidad>
		<entidad>ITEMVALORESNDCOMPRA</entidad>
		<atributo>RecargoMontoSinImpuestos</atributo>
		<tabla>ValNdComp</tabla>
		<campo>jrecmntsi</campo>
		<alta>false</alta>
		<tipodato>N</tipodato>
		<longitud>15</longitud>
		<decimales>2</decimales>
		<dominio>NUMERICO</dominio>
		<claveprimaria>false</claveprimaria>
		<claveforanea/>
		<muestrarelacion>false</muestrarelacion>
		<valorsugerido/>
		<obligatorio>false</obligatorio>
		<atributoforaneo/>
	</diccionarioentidad>
	<diccionarioentidad>
		<entidad>ITEMVALORESNDCOMPRA</entidad>
		<atributo>MontoAMonedaSistema</atributo>
		<tabla>ValNdComp</tabla>
		<campo>Montosiste</campo>
		<alta>false</alta>
		<tipodato>N</tipodato>
		<longitud>15</longitud>
		<decimales>2</decimales>
		<dominio>NUMERICO</dominio>
		<claveprimaria>false</claveprimaria>
		<claveforanea/>
		<muestrarelacion>false</muestrarelacion>
		<valorsugerido/>
		<obligatorio>false</obligatorio>
		<atributoforaneo/>
	</diccionarioentidad>
	<diccionarioentidad>
		<entidad>ITEMVALORESNDCOMPRA</entidad>
		<atributo>RecargoSinPercepciones</atributo>
		<tabla>ValNdComp</tabla>
		<campo>jrrecsperc</campo>
		<alta>false</alta>
		<tipodato>N</tipodato>
		<longitud>15</longitud>
		<decimales>2</decimales>
		<dominio>NUMERICO</dominio>
		<claveprimaria>false</claveprimaria>
		<claveforanea/>
		<muestrarelacion>false</muestrarelacion>
		<valorsugerido/>
		<obligatorio>false</obligatorio>
		<atributoforaneo/>
	</diccionarioentidad>
	<diccionarioentidad>
		<entidad>ITEMVALORESNDCOMPRA</entidad>
		<atributo>NumeroValeDeCambio</atributo>
		<tabla>ValNdComp</tabla>
		<campo>ValeCambio</campo>
		<alta>false</alta>
		<tipodato>C</tipodato>
		<longitud>38</longitud>
		<decimales>0</decimales>
		<dominio>CODIGO</dominio>
		<claveprimaria>false</claveprimaria>
		<claveforanea>VALEDECAMBIO</claveforanea>
		<muestrarelacion>false</muestrarelacion>
		<valorsugerido/>
		<obligatorio>false</obligatorio>
		<atributoforaneo/>
	</diccionarioentidad>
	<diccionarioentidad>
		<entidad>ITEMVALORESNDCOMPRA</entidad>
		<atributo>PermiteVuelto</atributo>
		<tabla>ValNdComp</tabla>
		<campo>permvuelto</campo>
		<alta>false</alta>
		<tipodato>L</tipodato>
		<longitud>1</longitud>
		<decimales>0</decimales>
		<dominio>SINOBOOL</dominio>
		<claveprimaria>false</claveprimaria>
		<claveforanea/>
		<muestrarelacion>false</muestrarelacion>
		<valorsugerido/>
		<obligatorio>false</obligatorio>
		<atributoforaneo>Valor.PermiteVuelto</atributoforaneo>
	</diccionarioentidad>
	<diccionarioentidad>
		<entidad>ITEMVALORESNDCOMPRA</entidad>
		<atributo>IdItemComponente</atributo>
		<tabla>ValNdComp</tabla>
		<campo>guidComp</campo>
		<alta>false</alta>
		<tipodato>C</tipodato>
		<longitud>20</longitud>
		<decimales>0</decimales>
		<dominio>CARACTER</dominio>
		<claveprimaria>false</claveprimaria>
		<claveforanea/>
		<muestrarelacion>false</muestrarelacion>
		<valorsugerido/>
		<obligatorio>false</obligatorio>
		<atributoforaneo/>
	</diccionarioentidad>
</VFPData>
